ubermagtable/__init__.py
ubermagtable/interact.py
ubermagtable/table.py
ubermagtable/tests/__init__.py
ubermagtable/tests/test_init.py
ubermagtable/tests/test_interact.py
ubermagtable/tests/test_table.py
ubermagtable/tests/test_util.py
ubermagtable/tests/test_sample/mumax3-file1.txt
ubermagtable/tests/test_sample/oommf-hysteresis1.odt
ubermagtable/tests/test_sample/oommf-issue1.odt
ubermagtable/tests/test_sample/oommf-mel-file.odt
ubermagtable/tests/test_sample/oommf-minsteps.odt
ubermagtable/tests/test_sample/oommf-new-file1.odt
ubermagtable/tests/test_sample/oommf-new-file2.odt
ubermagtable/tests/test_sample/oommf-new-file3.odt
ubermagtable/tests/test_sample/oommf-new-file4.odt
ubermagtable/tests/test_sample/oommf-new-file5.odt
ubermagtable/tests/test_sample/oommf-old-file1.odt
ubermagtable/tests/test_sample/oommf-old-file2.odt
ubermagtable/tests/test_sample/oommf-old-file3.odt
ubermagtable/tests/test_sample/oommf-old-file4.odt
ubermagtable/tests/test_sample/oommf-old-file5.odt
ubermagtable/tests/test_sample/oommf-old-file6.odt
ubermagtable/tests/test_sample/oommf-old-file7.odt
ubermagtable/tests/test_sample/oommf-old-file8.odt
ubermagtable/util/__init__.py
ubermagtable/util/plotting-style.mplstyle
ubermagtable/util/util.py
ubermagtable-0.62.0.dist-info/licenses/LICENSE
ubermagtable-0.62.0.dist-info/METADATA
ubermagtable-0.62.0.dist-info/WHEEL
ubermagtable-0.62.0.dist-info/top_level.txt
ubermagtable-0.62.0.dist-info/RECORD
