Metadata-Version: 2.4
Name: ubermagtable
Version: 0.62.0
Summary: Python package for manipulating tabular data.
Author: Marijan Beg, Martin Lang, Ryan A. Pepper, Thomas Kluyver, Samuel Holt, Swapneel Amit Pathak, Hans Fangohr
License-Expression: BSD-3-Clause
Project-URL: homepage, https://ubermag.github.io
Project-URL: documentation, https://ubermag.github.io/documentation/ubermagtable
Project-URL: repository, https://github.com/ubermag/ubermagtable
Classifier: Development Status :: 5 - Production/Stable
Classifier: Intended Audience :: Education
Classifier: Intended Audience :: Developers
Classifier: Intended Audience :: Science/Research
Classifier: Natural Language :: English
Classifier: Operating System :: MacOS
Classifier: Operating System :: Microsoft :: Windows
Classifier: Operating System :: Unix
Classifier: Programming Language :: Python :: 3 :: Only
Classifier: Topic :: Scientific/Engineering :: Physics
Classifier: Topic :: Scientific/Engineering :: Mathematics
Classifier: Topic :: Scientific/Engineering :: Visualization
Requires-Python: >=3.9
License-File: LICENSE
Requires-Dist: ubermagutil>=0.64.0
Requires-Dist: pandas>=1.1
Requires-Dist: matplotlib>=3.3
Requires-Dist: ipywidgets>=7.5
Provides-Extra: dev
Requires-Dist: build; extra == "dev"
Requires-Dist: invoke; extra == "dev"
Requires-Dist: nbval; extra == "dev"
Requires-Dist: pre-commit; extra == "dev"
Requires-Dist: pytest-cov; extra == "dev"
Requires-Dist: twine; extra == "dev"
Requires-Dist: tomli; python_version < "3.11" and extra == "dev"
Dynamic: license-file
